django_glossa-1.0.3.dist-info/DESCRIPTION.rst
django_glossa-1.0.3.dist-info/METADATA
django_glossa-1.0.3.dist-info/RECORD
django_glossa-1.0.3.dist-info/WHEEL
django_glossa-1.0.3.dist-info/metadata.json
django_glossa-1.0.3.dist-info/top_level.txt
glossario/__init__.py
glossario/admin.py
glossario/cms_apps.py
glossario/helpers.py
glossario/models.py
glossario/settings.py
glossario/sitemap.py
glossario/urls.py
glossario/views.py
glossario/locale/it/LC_MESSAGES/django.mo
glossario/locale/it/LC_MESSAGES/django.po
glossario/south_migrations/0001_initial.py
glossario/south_migrations/0002_auto__chg_field_term_definition.py
glossario/south_migrations/__init__.py
glossario/templates/glossario/base.html
glossario/templates/glossario/index.html
glossario/templates/glossario/term_detail.html
glossario/templates/glossario/term_list.html
glossario/templates/glossario/terms_index.html
